Workbook

Sheet Assumptions
A1: Privé Structured Products Engine — Value-Capture Model: Assumptions
A2: Legend: blue text on yellow = adjustable input (edit these). Black = formula. Green = link from another sheet.
A4: ID | B4: Assumption | C4: Value | D4: Notes / source
A5: A2 | B5: Annual call/maturity event rate | C5: 0.73 | D5: iCapital 2024: ~$39bn called = 73% of callable population; ~12m avg duration. Range 65–80%.
A6: A3a | B6: Capture-rate uplift — banks (pp of event volume) | C6: 0.1 | D6: Banks baseline capture ~50–60%; uplift +5pp conservative / +15pp upside. REPLACE WITH PILOT TELEMETRY.
A7: A3b | B7: Capture-rate uplift — EAMs (pp of event volume) | C7: 0.15 | D7: EAMs largely spreadsheet-driven; lower baseline, higher uplift. Range +5 to +20pp.
A8: A4 | B8: Sales margin on SP flow (fraction) | C8: 0.01 | D8: Typical Asian PB/EAM upfront margin on FCN/ELN/autocall: 0.5–1.5% (100bps base).
A9: A1a | B9: Value-capture share — EAM / mid-tier price ceiling | C9: 0.15 | D9: Software's sustainable share of value created: 10–20%.
A10: A1b | B10: Value-capture share — large bank | C10: 0.1 | D10: Large buyers pay a lower share: 8–15%.
A11: A6a | B11: EAM fee yield on AUM | C11: 0.006 | D11: Typical EAM revenue 0.5–1.0% of AUM.
A12: A6b | B12: SP share of EAM revenue | C12: 0.2 | D12: SPs ~20%+ of revenue at many Asian wealth platforms.
A13: A12 | B13: SP allocation within EAM AUM | C13: 0.2 | D13: 15–25% typical; drives SP book from AUM.

Sheet Value Model
A1: Value-Capture Model — Scenarios (all formulas live; edit blue/yellow cells here or on Assumptions)
A3: Line item | B3: EAM (Band B) | C3: Mid-tier private bank | D3: Large bank | E3: Formula logic
A4: Client AUM ($) — EAM only | B4: 500000000 | E4: Input
A5: SP book size ($) | B5: =B4*Assumptions!$C$13 -> 100000000 | C5: 5000000000 | D5: 20000000000 | E5: EAM: AUM × SP allocation (A12). Banks: direct input.
A6: Annual call/maturity event volume ($) | B6: =B5*Assumptions!$C$5 -> 73000000 | C6: =C5*Assumptions!$C$5 -> 3650000000 | D6: =D5*Assumptions!$C$5 -> 14600000000 | E6: SP book × call rate (A2)
A7: Capture-rate uplift applied | B7: =Assumptions!$C$7 -> 0.15 | C7: =Assumptions!$C$6 -> 0.1 | D7: =Assumptions!$C$6 -> 0.1 | E7: EAMs use A3b; banks A3a
A8: Incremental captured reinvestment flow ($) | B8: =B6*B7 -> 10950000 | C8: =C6*C7 -> 365000000 | D8: =D6*D7 -> 1460000000 | E8: Event volume × uplift
A9: Incremental margin created p.a. ($) | B9: =B8*Assumptions!$C$8 -> 109500 | C9: =C8*Assumptions!$C$8 -> 3650000 | D9: =D8*Assumptions!$C$8 -> 14600000 | E9: Flow × sales margin (A4)
A10: Value-capture share applied | B10: =Assumptions!$C$9 -> 0.15 | C10: =Assumptions!$C$9 -> 0.15 | D10: =Assumptions!$C$10 -> 0.1 | E10: A1a for EAM/mid-tier; A1b for large bank
A11: Defensible annual software price (ceiling) ($) | B11: =B9*B10 -> 16425 | C11: =C9*C10 -> 547500 | D11: =D9*D10 -> 1460000 | E11: Incremental margin × capture share
A13: Proposed target annual price (from methodology doc) | B13: 20000 | C13: 575000 | D13: 1350000 | E13: EAM 'Manage' Band B annual fee; banks: full-stack target ACV (all three tiers)
A14: Proposed price as % of value created | B14: =IF(B9=0,0,B13/B9) -> 0.1826484 | C14: =IF(C9=0,0,C13/C9) -> 0.15753425 | D14: =IF(D9=0,0,D13/D9) -> 0.092465753 | E14: Should sit ~8–20%. Above 25% = overpriced; below 8% = money left on table.
A16: EAM affordability check
A17: EAM total revenue ($) | B17: =B4*Assumptions!$C$11 -> 3000000
A18: EAM SP-attributable revenue ($) | B18: =B17*Assumptions!$C$12 -> 600000
A19: Proposed price as % of SP revenue | B19: =IF(B18=0,0,B13/B18) -> 0.033333333 | E19: Keep under ~5% for a founder-signable 'no-brainer'.

Sheet Price Cards
A1: Price Cards — floor / target / stretch (annual, USD; static reference from methodology doc)
A3: EAM ladder (by SP book band: A <$50m, B $50–150m, C $150–400m)
A4: Rung | B4: Band A | C4: Band B | D4: Band C | E4: Floor | F4: Target | G4: Stretch
A5: Monitor (Tier 1) | B5: 6000 | C5: 10000 | D5: 15000 | E5: 5000 | F5: 10000 | G5: 18000
A6: Manage (Tier 2, incl. Monitor) | B6: 12000 | C6: 20000 | D6: 32000 | E6: 10000 | F6: 20000 | G6: 45000
A7: Build (Tier 3, incl. all; 2 creator seats) | B7: 18000 | C7: 30000 | D7: 48000 | E7: 15000 | F7: 30000 | G7: 60000
A9: Enterprise modules
A10: Module | B10: Mid-tier floor | C10: Mid-tier target | D10: Mid-tier stretch | E10: Large floor | F10: Large target | G10: Large stretch
A11: Tier 1 platform / data feed (per entity, per use case) | B11: 40000 | C11: 75000 | D11: 150000 | E11: 120000 | F11: 200000 | G11: 300000
A12: Tier 2 lifecycle + NBO (fixed, volume-tiered) | B12: 150000 | C12: 350000 | D12: 600000 | E12: 500000 | F12: 850000 | G12: 1400000
A13: Tier 3 builder (seats @$3k, min 25; or desk licence) | B13: 75000 | C13: 150000 | D13: 250000 | E13: 250000 | F13: 300000 | G13: 450000
A14: Full-stack ACV | B14: =SUM(B11:B13) -> 265000 | C14: =SUM(C11:C13) -> 575000 | D14: =SUM(D11:D13) -> 1000000 | E14: =SUM(E11:E13) -> 870000 | F14: =SUM(F11:F13) -> 1350000 | G14: =SUM(G11:G13) -> 2150000
A16: Implementation (one-time): EAM $0–2.5k · Mid-tier full stack $250–400k (target $300k) · Large bank $500k–1m. Pilot fee ($30–50k enterprise) 100% creditable against year-1 licence within 60 days of pilot end.

Sheet T2 Overlay Calc
A1: Optional Tier 2 bps overlay — trade 30% of fixed fee for capped upside
A3: Tier 2 target fixed fee ($) | B3: 350000
A4: Fixed-fee reduction if overlay elected | B4: 0.3
A5: Overlay rate (bps p.a. on covered book above threshold) | B5: 0.75
A6: Covered-book threshold ($) | B6: 2000000000
A7: Covered SP book ($) | B7: 5000000000
A8: Cap multiple (× target fixed fee) | B8: 1.6
A9: Reduced fixed fee ($) | B9: =B3*(1-B4) -> 245000
A10: Overlay charge ($) | B10: =MAX(0,B7-B6)*B5/10000 -> 225000
A11: Total before cap ($) | B11: =B9+B10 -> 470000
A12: Cap ($) | B12: =B3*B8 -> 560000
A13: Total payable ($) | B13: =MIN(B11,B12) -> 470000
A15: Note: overlay meters on covered book (objective, from nightly position file), never on 'measured capture' — avoids attribution disputes at renewal.
